LICENSE
README.rst
setup.py
doublebellycluster/__init__.py
doublebellycluster/doublebellycluster.py
doublebellycluster/gausss.py
doublebellycluster/inter_dist.py
doublebellycluster/plots.py
doublebellycluster/seq_match.py
doublebellycluster.egg-info/PKG-INFO
doublebellycluster.egg-info/SOURCES.txt
doublebellycluster.egg-info/dependency_links.txt
doublebellycluster.egg-info/requires.txt
doublebellycluster.egg-info/top_level.txt
tests/0_tes.py
tests/__init__.py
tests/yadisk_test.py