Metadata-Version: 2.1
Name: doublebellycluster
Version: 1.0.0
Summary: Библиотека мин/макс на анализе плотности
Home-page: 
Author: George Pavlov
Author-email: pavlovgeorgem@yandex.ru
License: LGPLv3
Keywords: clustering intra_distance clustering-share-devide sequence-matching
Classifier: Development Status :: 5 - Production/Stable
Classifier: Intended Audience :: Education
Classifier: License :: OSI Approved :: GNU Lesser General Public License v3 (LGPLv3)
Classifier: License :: OSI Approved :: GNU Lesser General Public License v3 or later (LGPLv3+)
Classifier: Programming Language :: Python
Classifier: Programming Language :: Python :: 3
Classifier: Operating System :: OS Independent
Classifier: Topic :: Software Development :: Libraries
Classifier: Topic :: Software Development :: Libraries :: Python Modules
Requires-Python: >=3.5
License-File: LICENSE
